[
  {
    "mentor_first_name": "Alice",
    "mentor_last_name": "Wong",
    "mentor_email": "alice.wong@example.com",
    "mentor_phone": "0812345678",
    "company_id": 1
  },
  {
    "mentor_first_name": "Bob",
    "mentor_last_name": "Smith",
    "mentor_email": "bob.smith@example.com",
    "mentor_phone": "0823456789",
    "company_id": 2
  },
  {
    "mentor_first_name": "Carol",
    "mentor_last_name": "Lee",
    "mentor_email": "carol.lee@example.com",
    "mentor_phone": "0834567890",
    "company_id":1
  }
]